src/top.v
`timescale 1ns / 1ps
//////////////////////////////////////////////////////////////////////////////////
// Company: 
// Engineer: 
// 
// Create Date:    06:26:56 08/29/2025 
// Design Name: 
// Module Name:    top 
// Project Name: 
// Target Devices: 
// Tool versions: 
// Description: 
//
// Dependencies: 
//
// Revision: 
// Revision 0.01 - File Created
// Additional Comments: 
//
//////////////////////////////////////////////////////////////////////////////////
module top #(
  parameter integer F_CLK = 50_000_000,
  parameter integer BAUD  = 115200,
  parameter integer OSR   = 16
)(
  input  wire clk,
  input  wire rst_n,
  output reg  tick_osr,
  output reg  tick_bit
);

// ---- ceil(log2(value)) portable (không dùng $clog2) ----
  function integer clog2;
    input integer value;
    integer v, i;
  begin
    if (value <= 1) clog2 = 1;
    else begin
      v = value - 1;
      for (i = 0; v > 0; i = i + 1) v = v >> 1;
      clog2 = i;
    end
  end
  endfunction
  // ---- Tham số dẫn xuất ----
  localparam integer FTICK = BAUD * OSR;           // f_tick_osr
  localparam integer N0    = F_CLK / FTICK;        // floor(F_CLK/FTICK)
  localparam integer R     = F_CLK - N0*FTICK;     // phần dư (0..FTICK-1)
  localparam integer N_MIN = (N0 < 1) ? 1 : N0;    // chốt N>=1

  // width đủ chứa N hoặc N+1
  localparam integer CNT_W = clog2(N_MIN+1);       // (vì nạp N  -> đếm N..0)
  localparam integer OSR_W = clog2(OSR);
// ---- Trạng thái ----
  reg [CNT_W-1:0] cnt = {CNT_W{1'b0}};   // down-counter spacing
  reg [31:0]      acc = 32'd0;           // accumulator để quyết định N/N+1
  reg [OSR_W-1:0] osr = {OSR_W{1'b0}};   // đếm OSR để phát tick_bit
 // ---- Core ----
  always @(posedge clk or negedge rst_n) begin
    if (!rst_n) begin
      cnt <= {CNT_W{1'b0}};
      acc <= 32'd0;
      osr <= {OSR_W{1'b0}};
      tick_osr <= 1'b0;
      tick_bit <= 1'b0;
		end else begin
      tick_osr <= 1'b0;
      tick_bit <= 1'b0;

      if (cnt == 0) begin
        // phát tick_osr (1-clk)
        tick_osr <= 1'b1;
		 // gom OSR tick_osr -> 1 tick_bit
        if (osr == OSR-1) begin
          osr <= {OSR_W{1'b0}};
          tick_bit <= 1'b1;
        end else begin
          osr <= osr + 1'b1;
        end
		  // quyết định khoảng cách lần tới: N hoặc N+1
        if (R == 0) begin
          // chia đúng: khoảng cách cố định N_MIN
          // load N_MIN-1 để đếm xuống về 0 sau N_MIN chu kỳ
          cnt <= N_MIN - 1;
        end else if (acc + R >= FTICK) begin
          // lần này dùng (N_MIN + 1) chu kỳ
          acc <= acc + R - FTICK;
			  cnt <= N_MIN;          // N+1 -> load N
        end else begin
          // lần này dùng N_MIN chu kỳ
          acc <= acc + R;
          cnt <= N_MIN - 1;      // N   -> load N-1
        end

      end else begin
        // chưa đến tick -> đếm xuống
        cnt <= cnt - 1'b1;
      end
    end
  end
endmodule

tb/tb.v
`timescale 1ns / 1ps


module tb;

	// ======= Config =======
  parameter integer F_CLK = 50_000_000;   // 50 MHz
  parameter integer BAUD  = 115200;
  parameter integer OSR   = 16;

  // ======= Derived =======
  parameter integer FTICK = BAUD*OSR;
  parameter integer N0    = F_CLK / FTICK;             // floor
  parameter integer R     = F_CLK - N0*FTICK;          // remainder (0..FTICK-1)
  

  // ======= DUT =======
  reg  clk, rst_n;
  top uut (
		.clk(clk), 
		.rst_n(rst_n), 
		.tick_osr(tick_osr), 
		.tick_bit(tick_bit)
	);

  initial begin
        $dumpfile("sim/dump.vcd");   // dễ nhất: ghi ngay ở thư mục hiện tại
        $dumpvars(0, tb);        // tb = tên module testbench
        #1000 $finish;           // đảm bảo flush VCD và kết thúc mô phỏng
   end

   // clock 50 MHz
  initial clk = 1'b0;
  always #10 clk = ~clk;

  /// reset
  initial begin
    rst_n = 1'b0;
    repeat (5) @(posedge clk);
    rst_n = 1'b1;
  end

   // ======= Đếm chu kỳ & error =======
  integer cycle;
  integer errors;
  initial begin
    cycle  = 0;
    errors = 0;
  end
  always @(posedge clk) begin
    if (rst_n) cycle <= cycle + 1; else cycle <= 0;
  end
  // ======= Log cấu hình =======
  initial begin
    $timeformat(-9,0," ns",10);
    $display("CFG(FRAC): F_CLK=%0d, BAUD=%0d, OSR=%0d => FTICK=%0d, N0=%0d, R=%0d",
              F_CLK, BAUD, OSR, FTICK, N0, R);
  end
 // ======= Check A: spacing ∈ {N0, N0+1}, đếm tần suất (N0+1) =======
  integer last_tick_cycle;
  integer delta;
  integer cnt_N;
  integer cnt_Np1;
  integer intervals;
  initial begin
    last_tick_cycle = -1;
    delta = 0;
    cnt_N = 0;
    cnt_Np1 = 0;
    intervals = 0;
  end
  always @(posedge clk) begin
    if (rst_n && tick_osr) begin
      if (last_tick_cycle >= 0) begin
        delta = cycle - last_tick_cycle;
        intervals = intervals + 1;
  if (delta == N0)        cnt_N   = cnt_N   + 1;
        else if (delta == N0+1) cnt_Np1 = cnt_Np1 + 1;
        else begin
          $display("%t  ERROR: spacing %0d not in {%0d,%0d}", $time, delta, N0, N0+1);
          errors = errors + 1;
        end
      end
      last_tick_cycle = cycle;
    end
  end
  // ======= Check B: width 1-clk =======
  reg tick_osr_d;
  reg tick_bit_d;
  initial begin
    tick_osr_d = 1'b0;
    tick_bit_d = 1'b0;
  end
  
  always @(posedge clk) begin
    tick_osr_d <= tick_osr;
    tick_bit_d <= tick_bit;
    if (rst_n) begin
      if (tick_osr_d && tick_osr) begin
        $display("%t  ERROR: tick_osr width > 1 clk", $time);
        errors = errors + 1;
      end
      if (tick_bit_d && tick_bit) begin
        $display("%t  ERROR: tick_bit width > 1 clk", $time);
        errors = errors + 1;
      end
    end
  end
  // ======= Check C: mỗi OSR tick_osr -> 1 tick_bit =======
  integer osr_count;
  initial osr_count = 0;
  always @(posedge clk) begin
    if (!rst_n) osr_count <= 0;
    else if (tick_osr) begin
      if (osr_count == OSR-1) begin
        if (!tick_bit) begin
          $display("%t  ERROR: expected tick_bit on OSR-th tick_osr", $time);
          errors = errors + 1;
        end
		  osr_count <= 0;
      end else begin
        if (tick_bit) begin
          $display("%t  ERROR: unexpected tick_bit before OSR ticks", $time);
          errors = errors + 1;
        end
        osr_count <= osr_count + 1;
      end
    end
  end
   // ======= Kết thúc theo sự kiện: sau đủ số intervals =======
  // Mục tiêu: thu thập ~2000 intervals để ước lượng tần suất N0+1
  integer target_intervals;
  integer expected_Np1;
  integer tol;
  integer diff;

  initial begin
    target_intervals = 2000;  // có thể tăng/giảm
    // chờ reset xong
    wait (rst_n==1'b1);
    // chờ đủ số khoảng cách để thống kê
    wait (intervals >= target_intervals);
	 if (R == 0) begin
      if (cnt_Np1 != 0) begin
        $display("ERROR: R==0 nhưng vẫn có khoảng cách N0+1");
        errors = errors + 1;
      end
		 end else begin
      // p ≈ R/FTICK; expected_Np1 ≈ p * intervals; dung sai nhỏ
      expected_Np1 = (R * intervals) / FTICK;
      tol = (intervals/100); if (tol < 5) tol = 5;  // ±1% hoặc tối thiểu 5
      diff = (cnt_Np1 > expected_Np1) ? (cnt_Np1 - expected_Np1)
                                      : (expected_Np1 - cnt_Np1);
		if (diff > tol) begin
        $display("WARN: cnt_Np1=%0d, expected~%0d +/- %0d (intervals=%0d)",
                  cnt_Np1, expected_Np1, tol, intervals);
        // nếu muốn nghiêm hơn: errors = errors + 1;
      end
    end

  
   
    if (errors==0) $display("TB PASS (no errors).");
    else           $display("TB FAIL: %0d error(s).", errors);

    #1 $finish;
  end



endmodule

sim/dump.vcd
$date
	Fri Aug 29 15:32:51 2025
$end
$version
	Icarus Verilog
$end
$timescale
	1ps
$end
$scope module tb $end
$var wire 1 ! tick_osr $end
$var wire 1 " tick_bit $end
$var parameter 32 # BAUD $end
$var parameter 32 $ FTICK $end
$var parameter 32 % F_CLK $end
$var parameter 32 & N0 $end
$var parameter 32 ' OSR $end
$var parameter 32 ( R $end
$var reg 1 ) clk $end
$var reg 1 * rst_n $end
$var reg 1 + tick_bit_d $end
$var reg 1 , tick_osr_d $end
$var integer 32 - cnt_N [31:0] $end
$var integer 32 . cnt_Np1 [31:0] $end
$var integer 32 / cycle [31:0] $end
$var integer 32 0 delta [31:0] $end
$var integer 32 1 diff [31:0] $end
$var integer 32 2 errors [31:0] $end
$var integer 32 3 expected_Np1 [31:0] $end
$var integer 32 4 intervals [31:0] $end
$var integer 32 5 last_tick_cycle [31:0] $end
$var integer 32 6 osr_count [31:0] $end
$var integer 32 7 target_intervals [31:0] $end
$var integer 32 8 tol [31:0] $end
$scope module uut $end
$var wire 1 ) clk $end
$var wire 1 * rst_n $end
$var parameter 32 9 BAUD $end
$var parameter 32 : CNT_W $end
$var parameter 32 ; FTICK $end
$var parameter 32 < F_CLK $end
$var parameter 32 = N0 $end
$var parameter 32 > N_MIN $end
$var parameter 32 ? OSR $end
$var parameter 32 @ OSR_W $end
$var parameter 32 A R $end
$var reg 32 B acc [31:0] $end
$var reg 5 C cnt [4:0] $end
$var reg 4 D osr [3:0] $end
$var reg 1 " tick_bit $end
$var reg 1 ! tick_osr $end
$scope function clog2 $end
$var integer 32 E i [31:0] $end
$var integer 32 F v [31:0] $end
$var integer 32 G value [31:0] $end
$upscope $end
$upscope $end
$upscope $end
$enddefinitions $end
$comment Show the parameter values. $end
$dumpall
b111001000010000000 A
b100 @
b10000 ?
b11011 >
b11011 =
b10111110101111000010000000 <
b111000010000000000000 ;
b101 :
b11100001000000000 9
b111001000010000000 (
b10000 '
b11011 &
b10111110101111000010000000 %
b111000010000000000000 $
b11100001000000000 #
$end
#0
$dumpvars
bx G
bx F
bx E
b0 D
b0 C
b0 B
bx 8
b11111010000 7
b0 6
b11111111111111111111111111111111 5
b0 4
bx 3
b0 2
bx 1
b0 0
b0 /
b0 .
b0 -
0,
0+
0*
0)
0"
0!
$end
#10000
1)
#20000
0)
#30000
1)
#40000
0)
#50000
1)
#60000
0)
#70000
1)
#80000
0)
#90000
b11010 C
b111001000010000000 B
b1 D
1!
1*
1)
#100000
0)
#110000
b11001 C
0!
b1 6
1,
b1 /
b0 5
1)
#120000
0)
#130000
b11000 C
b10 /
0,
1)
#140000
0)
#150000
b10111 C
b11 /
1)
#160000
0)
#170000
b10110 C
b100 /
1)
#180000
0)
#190000
b10101 C
b101 /
1)
#200000
0)
#210000
b10100 C
b110 /
1)
#220000
0)
#230000
b10011 C
b111 /
1)
#240000
0)
#250000
b10010 C
b1000 /
1)
#260000
0)
#270000
b10001 C
b1001 /
1)
#280000
0)
#290000
b10000 C
b1010 /
1)
#300000
0)
#310000
b1111 C
b1011 /
1)
#320000
0)
#330000
b1110 C
b1100 /
1)
#340000
0)
#350000
b1101 C
b1101 /
1)
#360000
0)
#370000
b1100 C
b1110 /
1)
#380000
0)
#390000
b1011 C
b1111 /
1)
#400000
0)
#410000
b1010 C
b10000 /
1)
#420000
0)
#430000
b1001 C
b10001 /
1)
#440000
0)
#450000
b1000 C
b10010 /
1)
#460000
0)
#470000
b111 C
b10011 /
1)
#480000
0)
#490000
b110 C
b10100 /
1)
#500000
0)
#510000
b101 C
b10101 /
1)
#520000
0)
#530000
b100 C
b10110 /
1)
#540000
0)
#550000
b11 C
b10111 /
1)
#560000
0)
#570000
b10 C
b11000 /
1)
#580000
0)
#590000
b1 C
b11001 /
1)
#600000
0)
#610000
b0 C
b11010 /
1)
#620000
0)
#630000
b11010 C
b1110010000100000000 B
b10 D
1!
b11011 /
1)
#640000
0)
#650000
b11001 C
0!
b11100 /
1,
b10 6
b11011 5
b1 -
b1 4
b11011 0
1)
#660000
0)
#670000
b11000 C
0,
b11101 /
1)
#680000
0)
#690000
b10111 C
b11110 /
1)
#700000
0)
#710000
b10110 C
b11111 /
1)
#720000
0)
#730000
b10101 C
b100000 /
1)
#740000
0)
#750000
b10100 C
b100001 /
1)
#760000
0)
#770000
b10011 C
b100010 /
1)
#780000
0)
#790000
b10010 C
b100011 /
1)
#800000
0)
#810000
b10001 C
b100100 /
1)
#820000
0)
#830000
b10000 C
b100101 /
1)
#840000
0)
#850000
b1111 C
b100110 /
1)
#860000
0)
#870000
b1110 C
b100111 /
1)
#880000
0)
#890000
b1101 C
b101000 /
1)
#900000
0)
#910000
b1100 C
b101001 /
1)
#920000
0)
#930000
b1011 C
b101010 /
1)
#940000
0)
#950000
b1010 C
b101011 /
1)
#960000
0)
#970000
b1001 C
b101100 /
1)
#980000
0)
#990000
b1000 C
b101101 /
1)
